datanodeclient/__init__.py
datanodeclient/api_client.py
datanodeclient/configuration.py
datanodeclient/rest.py
datanodeclient/api/__init__.py
datanodeclient/api/annotation_api.py
datanodeclient/api/annotation_store_api.py
datanodeclient/api/dataset_api.py
datanodeclient/api/fhir_store_api.py
datanodeclient/api/note_api.py
datanodeclient/api/patient_api.py
datanodeclient/api/service_api.py
datanodeclient/models/__init__.py
datanodeclient/models/annotation.py
datanodeclient/models/annotation_store.py
datanodeclient/models/dataset.py
datanodeclient/models/error.py
datanodeclient/models/fhir_store.py
datanodeclient/models/note.py
datanodeclient/models/page_of_annotation_stores.py
datanodeclient/models/page_of_annotations.py
datanodeclient/models/page_of_datasets.py
datanodeclient/models/page_of_fhir_stores.py
datanodeclient/models/page_of_notes.py
datanodeclient/models/page_of_patients.py
datanodeclient/models/patient.py
datanodeclient/models/service.py
datanodeclient-1.0.0.dist-info/METADATA
datanodeclient-1.0.0.dist-info/WHEEL
datanodeclient-1.0.0.dist-info/top_level.txt
datanodeclient-1.0.0.dist-info/RECORD
