Metadata-Version: 2.1
Name: datanodeclient
Version: 1.0.0
Summary: NLP Sandbox Data Node API
Home-page: UNKNOWN
Author: The NLP Sandbox Team
Author-email: thomas.schaffter@sagebionetworks.org
License: Apache 2.0
Keywords: OpenAPI,OpenAPI-Generator,NLP Sandbox Data Node API
Platform: UNKNOWN
Requires-Dist: urllib3 (>=1.15)
Requires-Dist: six (>=1.10)
Requires-Dist: certifi
Requires-Dist: python-dateutil
